[
  {
    "id": "https://openalex.org/W1983140057",
    "title": "Embodied Meanings, Isotypes, and Aesthetical Ideas",
    "relevance_score": 11.542346,
    "doi": "https://doi.org/10.1111/j.1540-594x.2007.00243.x",
    "topic_ids": [
      "C100609095",
      "C107038049",
      "C144024400",
      "C142362112",
      "C111472728",
      "C138885662"
    ],
    "best_pdf": "https://academic.oup.com/jaac/article-pdf/65/1/121/34524215/jaac_v65_1_121.pdf",
    "backup_pdf": "https://doi.org/10.1111/j.1540-594x.2007.00243.x",
    "raw": {
      "id": "https://openalex.org/W1983140057",
      "display_name": "Embodied Meanings, Isotypes, and Aesthetical Ideas",
      "relevance_score": 11.542346,
      "doi": "https://doi.org/10.1111/j.1540-594x.2007.00243.x",
      "concepts": [
        {
          "id": "https://openalex.org/C100609095",
          "wikidata": "https://www.wikidata.org/wiki/Q1335050",
          "display_name": "Embodied cognition",
          "level": 2,
          "score": 0.9075372
        },
        {
          "id": "https://openalex.org/C107038049",
          "wikidata": "https://www.wikidata.org/wiki/Q35986",
          "display_name": "Aesthetics",
          "level": 1,
          "score": 0.57179534
        },
        {
          "id": "https://openalex.org/C144024400",
          "wikidata": "https://www.wikidata.org/wiki/Q21201",
          "display_name": "Sociology",
          "level": 0,
          "score": 0.36313948
        },
        {
          "id": "https://openalex.org/C142362112",
          "wikidata": "https://www.wikidata.org/wiki/Q735",
          "display_name": "Art",
          "level": 0,
          "score": 0.35818094
        },
        {
          "id": "https://openalex.org/C111472728",
          "wikidata": "https://www.wikidata.org/wiki/Q9471",
          "display_name": "Epistemology",
          "level": 1,
          "score": 0.31572878
        },
        {
          "id": "https://openalex.org/C138885662",
          "wikidata": "https://www.wikidata.org/wiki/Q5891",
          "display_name": "Philosophy",
          "level": 0,
          "score": 0.19818509
        }
      ],
      "primary_location": {
        "is_oa": true,
        "landing_page_url": "https://doi.org/10.1111/j.1540-594x.2007.00243.x",
        "pdf_url": "https://academic.oup.com/jaac/article-pdf/65/1/121/34524215/jaac_v65_1_121.pdf",
        "source": {
          "id": "https://openalex.org/S26308392",
          "display_name": "Journal of Aesthetics and Art Criticism",
          "issn_l": "0021-8529",
          "issn": [
            "0021-8529",
            "1540-6245"
          ],
          "is_oa": false,
          "is_in_doaj": false,
          "is_indexed_in_scopus": true,
          "is_core": true,
          "host_organization": "https://openalex.org/P4310311648",
          "host_organization_name": "Oxford University Press",
          "host_organization_lineage": [
            "https://openalex.org/P4310311647",
            "https://openalex.org/P4310311648"
          ],
          "host_organization_lineage_names": [
            "University of Oxford",
            "Oxford University Press"
          ],
          "type": "journal"
        },
        "license": null,
        "license_id": null,
        "version": "publishedVersion",
        "is_accepted": true,
        "is_published": true
      },
      "open_access": {
        "is_oa": true,
        "oa_status": "bronze",
        "oa_url": "https://academic.oup.com/jaac/article-pdf/65/1/121/34524215/jaac_v65_1_121.pdf",
        "any_repository_has_fulltext": false
      },
      "locations": [
        {
          "is_oa": true,
          "landing_page_url": "https://doi.org/10.1111/j.1540-594x.2007.00243.x",
          "pdf_url": "https://academic.oup.com/jaac/article-pdf/65/1/121/34524215/jaac_v65_1_121.pdf",
          "source": {
            "id": "https://openalex.org/S26308392",
            "display_name": "Journal of Aesthetics and Art Criticism",
            "issn_l": "0021-8529",
            "issn": [
              "0021-8529",
              "1540-6245"
            ],
            "is_oa": false,
            "is_in_doaj": false,
            "is_indexed_in_scopus": true,
            "is_core": true,
            "host_organization": "https://openalex.org/P4310311648",
            "host_organization_name": "Oxford University Press",
            "host_organization_lineage": [
              "https://openalex.org/P4310311647",
              "https://openalex.org/P4310311648"
            ],
            "host_organization_lineage_names": [
              "University of Oxford",
              "Oxford University Press"
            ],
            "type": "journal"
          },
          "license": null,
          "license_id": null,
          "version": "publishedVersion",
          "is_accepted": true,
          "is_published": true
        }
      ],
      "best_oa_location": {
        "is_oa": true,
        "landing_page_url": "https://doi.org/10.1111/j.1540-594x.2007.00243.x",
        "pdf_url": "https://academic.oup.com/jaac/article-pdf/65/1/121/34524215/jaac_v65_1_121.pdf",
        "source": {
          "id": "https://openalex.org/S26308392",
          "display_name": "Journal of Aesthetics and Art Criticism",
          "issn_l": "0021-8529",
          "issn": [
            "0021-8529",
            "1540-6245"
          ],
          "is_oa": false,
          "is_in_doaj": false,
          "is_indexed_in_scopus": true,
          "is_core": true,
          "host_organization": "https://openalex.org/P4310311648",
          "host_organization_name": "Oxford University Press",
          "host_organization_lineage": [
            "https://openalex.org/P4310311647",
            "https://openalex.org/P4310311648"
          ],
          "host_organization_lineage_names": [
            "University of Oxford",
            "Oxford University Press"
          ],
          "type": "journal"
        },
        "license": null,
        "license_id": null,
        "version": "publishedVersion",
        "is_accepted": true,
        "is_published": true
      }
    }
  },
  {
    "id": "https://openalex.org/W1991287739",
    "title": "Which strategies are used against insect pests: a survey in 120 institutions of public heritage",
    "relevance_score": 3.6925786,
    "doi": "https://doi.org/10.4081/jear.2011.137",
    "topic_ids": [
      "C2776451879",
      "C2780510313",
      "C86803240",
      "C2994141551",
      "C123963621",
      "C2777612826",
      "C18903297",
      "C36289849",
      "C144024400",
      "C59822182",
      "C6557445"
    ],
    "best_pdf": "https://www.pagepressjournals.org/index.php/jear/article/download/jear.2011.137/205",
    "backup_pdf": "https://doi.org/10.4081/jear.2011.137",
    "raw": {
      "id": "https://openalex.org/W1991287739",
      "display_name": "Which strategies are used against insect pests: a survey in 120 institutions of public heritage",
      "relevance_score": 3.6925786,
      "doi": "https://doi.org/10.4081/jear.2011.137",
      "concepts": [
        {
          "id": "https://openalex.org/C2776451879",
          "wikidata": "https://www.wikidata.org/wiki/Q1292038",
          "display_name": "Infestation",
          "level": 2,
          "score": 0.8897556
        },
        {
          "id": "https://openalex.org/C2780510313",
          "wikidata": "https://www.wikidata.org/wiki/Q178706",
          "display_name": "Institution",
          "level": 2,
          "score": 0.74461573
        },
        {
          "id": "https://openalex.org/C86803240",
          "wikidata": "https://www.wikidata.org/wiki/Q420",
          "display_name": "Biology",
          "level": 0,
          "score": 0.5522617
        },
        {
          "id": "https://openalex.org/C2994141551",
          "wikidata": "https://www.wikidata.org/wiki/Q5333460",
          "display_name": "Insect pest",
          "level": 2,
          "score": 0.52872896
        },
        {
          "id": "https://openalex.org/C123963621",
          "wikidata": "https://www.wikidata.org/wiki/Q525309",
          "display_name": "Integrated pest management",
          "level": 2,
          "score": 0.4945893
        },
        {
          "id": "https://openalex.org/C2777612826",
          "wikidata": "https://www.wikidata.org/wiki/Q1390",
          "display_name": "Insect",
          "level": 2,
          "score": 0.434365
        },
        {
          "id": "https://openalex.org/C18903297",
          "wikidata": "https://www.wikidata.org/wiki/Q7150",
          "display_name": "Ecology",
          "level": 1,
          "score": 0.40686268
        },
        {
          "id": "https://openalex.org/C36289849",
          "wikidata": "https://www.wikidata.org/wiki/Q34749",
          "display_name": "Social science",
          "level": 1,
          "score": 0.2271735
        },
        {
          "id": "https://openalex.org/C144024400",
          "wikidata": "https://www.wikidata.org/wiki/Q21201",
          "display_name": "Sociology",
          "level": 0,
          "score": 0.21152878
        },
        {
          "id": "https://openalex.org/C59822182",
          "wikidata": "https://www.wikidata.org/wiki/Q441",
          "display_name": "Botany",
          "level": 1,
          "score": 0.16514018
        },
        {
          "id": "https://openalex.org/C6557445",
          "wikidata": "https://www.wikidata.org/wiki/Q173113",
          "display_name": "Agronomy",
          "level": 1,
          "score": 0.14888465
        }
      ],
      "primary_location": {
        "is_oa": true,
        "landing_page_url": "https://doi.org/10.4081/jear.2011.137",
        "pdf_url": "https://www.pagepressjournals.org/index.php/jear/article/download/jear.2011.137/205",
        "source": {
          "id": "https://openalex.org/S2738218850",
          "display_name": "Journal of Entomological and Acarological Research",
          "issn_l": "2038-324X",
          "issn": [
            "2038-324X",
            "2279-7084"
          ],
          "is_oa": true,
          "is_in_doaj": true,
          "is_indexed_in_scopus": true,
          "is_core": true,
          "host_organization": "https://openalex.org/P4310319913",
          "host_organization_name": "PAGEPress (Italy)",
          "host_organization_lineage": [
            "https://openalex.org/P4310319913"
          ],
          "host_organization_lineage_names": [
            "PAGEPress (Italy)"
          ],
          "type": "journal"
        },
        "license": "cc-by-nc",
        "license_id": "https://openalex.org/licenses/cc-by-nc",
        "version": "publishedVersion",
        "is_accepted": true,
        "is_published": true
      },
      "open_access": {
        "is_oa": true,
        "oa_status": "gold",
        "oa_url": "https://www.pagepressjournals.org/index.php/jear/article/download/jear.2011.137/205",
        "any_repository_has_fulltext": false
      },
      "locations": [
        {
          "is_oa": true,
          "landing_page_url": "https://doi.org/10.4081/jear.2011.137",
          "pdf_url": "https://www.pagepressjournals.org/index.php/jear/article/download/jear.2011.137/205",
          "source": {
            "id": "https://openalex.org/S2738218850",
            "display_name": "Journal of Entomological and Acarological Research",
            "issn_l": "2038-324X",
            "issn": [
              "2038-324X",
              "2279-7084"
            ],
            "is_oa": true,
            "is_in_doaj": true,
            "is_indexed_in_scopus": true,
            "is_core": true,
            "host_organization": "https://openalex.org/P4310319913",
            "host_organization_name": "PAGEPress (Italy)",
            "host_organization_lineage": [
              "https://openalex.org/P4310319913"
            ],
            "host_organization_lineage_names": [
              "PAGEPress (Italy)"
            ],
            "type": "journal"
          },
          "license": "cc-by-nc",
          "license_id": "https://openalex.org/licenses/cc-by-nc",
          "version": "publishedVersion",
          "is_accepted": true,
          "is_published": true
        },
        {
          "is_oa": false,
          "landing_page_url": "https://doaj.org/article/47f12638178742748c4df7addc170c96",
          "pdf_url": null,
          "source": {
            "id": "https://openalex.org/S4306401280",
            "display_name": "DOAJ (DOAJ: Directory of Open Access Journals)",
            "issn_l": null,
            "issn": null,
            "is_oa": true,
            "is_in_doaj": false,
            "is_indexed_in_scopus": false,
            "is_core": false,
            "host_organization": null,
            "host_organization_name": null,
            "host_organization_lineage": [],
            "host_organization_lineage_names": [],
            "type": "repository"
          },
          "license": null,
          "license_id": null,
          "version": null,
          "is_accepted": false,
          "is_published": false
        }
      ],
      "best_oa_location": {
        "is_oa": true,
        "landing_page_url": "https://doi.org/10.4081/jear.2011.137",
        "pdf_url": "https://www.pagepressjournals.org/index.php/jear/article/download/jear.2011.137/205",
        "source": {
          "id": "https://openalex.org/S2738218850",
          "display_name": "Journal of Entomological and Acarological Research",
          "issn_l": "2038-324X",
          "issn": [
            "2038-324X",
            "2279-7084"
          ],
          "is_oa": true,
          "is_in_doaj": true,
          "is_indexed_in_scopus": true,
          "is_core": true,
          "host_organization": "https://openalex.org/P4310319913",
          "host_organization_name": "PAGEPress (Italy)",
          "host_organization_lineage": [
            "https://openalex.org/P4310319913"
          ],
          "host_organization_lineage_names": [
            "PAGEPress (Italy)"
          ],
          "type": "journal"
        },
        "license": "cc-by-nc",
        "license_id": "https://openalex.org/licenses/cc-by-nc",
        "version": "publishedVersion",
        "is_accepted": true,
        "is_published": true
      }
    }
  },
  {
    "id": "https://openalex.org/W2289862484",
    "title": "Perceived distance and obesity: It's what you weigh, not what you think",
    "relevance_score": 2.7966537,
    "doi": "https://doi.org/10.1016/j.actpsy.2016.01.012",
    "topic_ids": [
      "C26760741",
      "C15744967",
      "C2780586474",
      "C2780791683",
      "C2776035688",
      "C77805123",
      "C60627051",
      "C511355011",
      "C147583825",
      "C138496976",
      "C46312422",
      "C71924100",
      "C121332964",
      "C142724271",
      "C62520636",
      "C169760540",
      "C126322002"
    ],
    "best_pdf": "https://www.sciencedirect.com/science/article/am/pii/S0001691816300129",
    "backup_pdf": "https://doi.org/10.1016/j.actpsy.2016.01.012",
    "raw": {
      "id": "https://openalex.org/W2289862484",
      "display_name": "Perceived distance and obesity: It's what you weigh, not what you think",
      "relevance_score": 2.7966537,
      "doi": "https://doi.org/10.1016/j.actpsy.2016.01.012",
      "concepts": [
        {
          "id": "https://openalex.org/C26760741",
          "wikidata": "https://www.wikidata.org/wiki/Q160402",
          "display_name": "Perception",
          "level": 2,
          "score": 0.80674326
        },
        {
          "id": "https://openalex.org/C15744967",
          "wikidata": "https://www.wikidata.org/wiki/Q9418",
          "display_name": "Psychology",
          "level": 0,
          "score": 0.7045797
        },
        {
          "id": "https://openalex.org/C2780586474",
          "wikidata": "https://www.wikidata.org/wiki/Q332428",
          "display_name": "Overweight",
          "level": 3,
          "score": 0.6475845
        },
        {
          "id": "https://openalex.org/C2780791683",
          "wikidata": "https://www.wikidata.org/wiki/Q846785",
          "display_name": "Action (physics)",
          "level": 2,
          "score": 0.5927271
        },
        {
          "id": "https://openalex.org/C2776035688",
          "wikidata": "https://www.wikidata.org/wiki/Q1606558",
          "display_name": "Affect (linguistics)",
          "level": 2,
          "score": 0.57445633
        },
        {
          "id": "https://openalex.org/C77805123",
          "wikidata": "https://www.wikidata.org/wiki/Q161272",
          "display_name": "Social psychology",
          "level": 1,
          "score": 0.55849844
        },
        {
          "id": "https://openalex.org/C60627051",
          "wikidata": "https://www.wikidata.org/wiki/Q1072278",
          "display_name": "Body shape",
          "level": 2,
          "score": 0.48333356
        },
        {
          "id": "https://openalex.org/C511355011",
          "wikidata": "https://www.wikidata.org/wiki/Q12174",
          "display_name": "Obesity",
          "level": 2,
          "score": 0.4609419
        },
        {
          "id": "https://openalex.org/C147583825",
          "wikidata": "https://www.wikidata.org/wiki/Q620876",
          "display_name": "Body weight",
          "level": 2,
          "score": 0.44522282
        },
        {
          "id": "https://openalex.org/C138496976",
          "wikidata": "https://www.wikidata.org/wiki/Q175002",
          "display_name": "Developmental psychology",
          "level": 1,
          "score": 0.3290034
        },
        {
          "id": "https://openalex.org/C46312422",
          "wikidata": "https://www.wikidata.org/wiki/Q11024",
          "display_name": "Communication",
          "level": 1,
          "score": 0.17721185
        },
        {
          "id": "https://openalex.org/C71924100",
          "wikidata": "https://www.wikidata.org/wiki/Q11190",
          "display_name": "Medicine",
          "level": 0,
          "score": 0.101777166
        },
        {
          "id": "https://openalex.org/C121332964",
          "wikidata": "https://www.wikidata.org/wiki/Q413",
          "display_name": "Physics",
          "level": 0,
          "score": 0.0
        },
        {
          "id": "https://openalex.org/C142724271",
          "wikidata": "https://www.wikidata.org/wiki/Q7208",
          "display_name": "Pathology",
          "level": 1,
          "score": 0.0
        },
        {
          "id": "https://openalex.org/C62520636",
          "wikidata": "https://www.wikidata.org/wiki/Q944",
          "display_name": "Quantum mechanics",
          "level": 1,
          "score": 0.0
        },
        {
          "id": "https://openalex.org/C169760540",
          "wikidata": "https://www.wikidata.org/wiki/Q207011",
          "display_name": "Neuroscience",
          "level": 1,
          "score": 0.0
        },
        {
          "id": "https://openalex.org/C126322002",
          "wikidata": "https://www.wikidata.org/wiki/Q11180",
          "display_name": "Internal medicine",
          "level": 1,
          "score": 0.0
        }
      ],
      "primary_location": {
        "is_oa": true,
        "landing_page_url": "https://doi.org/10.1016/j.actpsy.2016.01.012",
        "pdf_url": "https://www.sciencedirect.com/science/article/am/pii/S0001691816300129",
        "source": {
          "id": "https://openalex.org/S180067919",
          "display_name": "Acta Psychologica",
          "issn_l": "0001-6918",
          "issn": [
            "0001-6918",
            "1873-6297"
          ],
          "is_oa": true,
          "is_in_doaj": true,
          "is_indexed_in_scopus": true,
          "is_core": true,
          "host_organization": "https://openalex.org/P4310320990",
          "host_organization_name": "Elsevier BV",
          "host_organization_lineage": [
            "https://openalex.org/P4310320990"
          ],
          "host_organization_lineage_names": [
            "Elsevier BV"
          ],
          "type": "journal"
        },
        "license": "publisher-specific-oa",
        "license_id": "https://openalex.org/licenses/publisher-specific-oa",
        "version": "acceptedVersion",
        "is_accepted": true,
        "is_published": false
      },
      "open_access": {
        "is_oa": true,
        "oa_status": "bronze",
        "oa_url": "https://www.sciencedirect.com/science/article/am/pii/S0001691816300129",
        "any_repository_has_fulltext": false
      },
      "locations": [
        {
          "is_oa": true,
          "landing_page_url": "https://doi.org/10.1016/j.actpsy.2016.01.012",
          "pdf_url": "https://www.sciencedirect.com/science/article/am/pii/S0001691816300129",
          "source": {
            "id": "https://openalex.org/S180067919",
            "display_name": "Acta Psychologica",
            "issn_l": "0001-6918",
            "issn": [
              "0001-6918",
              "1873-6297"
            ],
            "is_oa": true,
            "is_in_doaj": true,
            "is_indexed_in_scopus": true,
            "is_core": true,
            "host_organization": "https://openalex.org/P4310320990",
            "host_organization_name": "Elsevier BV",
            "host_organization_lineage": [
              "https://openalex.org/P4310320990"
            ],
            "host_organization_lineage_names": [
              "Elsevier BV"
            ],
            "type": "journal"
          },
          "license": "publisher-specific-oa",
          "license_id": "https://openalex.org/licenses/publisher-specific-oa",
          "version": "acceptedVersion",
          "is_accepted": true,
          "is_published": false
        },
        {
          "is_oa": false,
          "landing_page_url": "https://pubmed.ncbi.nlm.nih.gov/26854404",
          "pdf_url": null,
          "source": {
            "id": "https://openalex.org/S4306525036",
            "display_name": "PubMed",
            "issn_l": null,
            "issn": null,
            "is_oa": false,
            "is_in_doaj": false,
            "is_indexed_in_scopus": false,
            "is_core": false,
            "host_organization": "https://openalex.org/I1299303238",
            "host_organization_name": "National Institutes of Health",
            "host_organization_lineage": [
              "https://openalex.org/I1299303238"
            ],
            "host_organization_lineage_names": [
              "National Institutes of Health"
            ],
            "type": "repository"
          },
          "license": null,
          "license_id": null,
          "version": null,
          "is_accepted": false,
          "is_published": false
        }
      ],
      "best_oa_location": {
        "is_oa": true,
        "landing_page_url": "https://doi.org/10.1016/j.actpsy.2016.01.012",
        "pdf_url": "https://www.sciencedirect.com/science/article/am/pii/S0001691816300129",
        "source": {
          "id": "https://openalex.org/S180067919",
          "display_name": "Acta Psychologica",
          "issn_l": "0001-6918",
          "issn": [
            "0001-6918",
            "1873-6297"
          ],
          "is_oa": true,
          "is_in_doaj": true,
          "is_indexed_in_scopus": true,
          "is_core": true,
          "host_organization": "https://openalex.org/P4310320990",
          "host_organization_name": "Elsevier BV",
          "host_organization_lineage": [
            "https://openalex.org/P4310320990"
          ],
          "host_organization_lineage_names": [
            "Elsevier BV"
          ],
          "type": "journal"
        },
        "license": "publisher-specific-oa",
        "license_id": "https://openalex.org/licenses/publisher-specific-oa",
        "version": "acceptedVersion",
        "is_accepted": true,
        "is_published": false
      }
    }
  },
  {
    "id": "https://openalex.org/W2946522947",
    "title": "Sounds of Loss: Church Bells, Place, and Time in the Habsburg Empire During the First World War*",
    "relevance_score": 2.346522,
    "doi": "https://doi.org/10.1093/pastj/gtz006",
    "topic_ids": [
      "C2778495208",
      "C95457728",
      "C2779793952",
      "C195244886",
      "C2776786559",
      "C2778355321",
      "C521449643",
      "C144024400",
      "C142362112",
      "C199539241",
      "C107038049",
      "C17744445",
      "C94625758"
    ],
    "best_pdf": "https://academic.oup.com/past/article-pdf/244/1/123/29021722/gtz010.pdf",
    "backup_pdf": "https://doi.org/10.1093/pastj/gtz006",
    "raw": {
      "id": "https://openalex.org/W2946522947",
      "display_name": "Sounds of Loss: Church Bells, Place, and Time in the Habsburg Empire During the First World War*",
      "relevance_score": 2.346522,
      "doi": "https://doi.org/10.1093/pastj/gtz006",
      "concepts": [
        {
          "id": "https://openalex.org/C2778495208",
          "wikidata": "https://www.wikidata.org/wiki/Q48349",
          "display_name": "Empire",
          "level": 2,
          "score": 0.7476426
        },
        {
          "id": "https://openalex.org/C95457728",
          "wikidata": "https://www.wikidata.org/wiki/Q309",
          "display_name": "History",
          "level": 0,
          "score": 0.5449847
        },
        {
          "id": "https://openalex.org/C2779793952",
          "wikidata": "https://www.wikidata.org/wiki/Q1553701",
          "display_name": "Religiosity",
          "level": 2,
          "score": 0.52986497
        },
        {
          "id": "https://openalex.org/C195244886",
          "wikidata": "https://www.wikidata.org/wiki/Q41493",
          "display_name": "Ancient history",
          "level": 1,
          "score": 0.4794418
        },
        {
          "id": "https://openalex.org/C2776786559",
          "wikidata": "https://www.wikidata.org/wiki/Q6241",
          "display_name": "Patriotism",
          "level": 3,
          "score": 0.46645516
        },
        {
          "id": "https://openalex.org/C2778355321",
          "wikidata": "https://www.wikidata.org/wiki/Q17079427",
          "display_name": "Identity (music)",
          "level": 2,
          "score": 0.4547845
        },
        {
          "id": "https://openalex.org/C521449643",
          "wikidata": "https://www.wikidata.org/wiki/Q6235",
          "display_name": "Nationalism",
          "level": 3,
          "score": 0.4416328
        },
        {
          "id": "https://openalex.org/C144024400",
          "wikidata": "https://www.wikidata.org/wiki/Q21201",
          "display_name": "Sociology",
          "level": 0,
          "score": 0.3949954
        },
        {
          "id": "https://openalex.org/C142362112",
          "wikidata": "https://www.wikidata.org/wiki/Q735",
          "display_name": "Art",
          "level": 0,
          "score": 0.2963708
        },
        {
          "id": "https://openalex.org/C199539241",
          "wikidata": "https://www.wikidata.org/wiki/Q7748",
          "display_name": "Law",
          "level": 1,
          "score": 0.26531833
        },
        {
          "id": "https://openalex.org/C107038049",
          "wikidata": "https://www.wikidata.org/wiki/Q35986",
          "display_name": "Aesthetics",
          "level": 1,
          "score": 0.19751173
        },
        {
          "id": "https://openalex.org/C17744445",
          "wikidata": "https://www.wikidata.org/wiki/Q36442",
          "display_name": "Political science",
          "level": 0,
          "score": 0.17997727
        },
        {
          "id": "https://openalex.org/C94625758",
          "wikidata": "https://www.wikidata.org/wiki/Q7163",
          "display_name": "Politics",
          "level": 2,
          "score": 0.095747024
        }
      ],
      "primary_location": {
        "is_oa": true,
        "landing_page_url": "https://doi.org/10.1093/pastj/gtz006",
        "pdf_url": "https://academic.oup.com/past/article-pdf/244/1/123/29021722/gtz010.pdf",
        "source": {
          "id": "https://openalex.org/S42922845",
          "display_name": "Past & Present",
          "issn_l": "0031-2746",
          "issn": [
            "0031-2746",
            "1477-464X"
          ],
          "is_oa": false,
          "is_in_doaj": false,
          "is_indexed_in_scopus": true,
          "is_core": false,
          "host_organization": "https://openalex.org/P4310311648",
          "host_organization_name": "Oxford University Press",
          "host_organization_lineage": [
            "https://openalex.org/P4310311647",
            "https://openalex.org/P4310311648"
          ],
          "host_organization_lineage_names": [
            "University of Oxford",
            "Oxford University Press"
          ],
          "type": "journal"
        },
        "license": "cc-by-nc-nd",
        "license_id": "https://openalex.org/licenses/cc-by-nc-nd",
        "version": "publishedVersion",
        "is_accepted": true,
        "is_published": true
      },
      "open_access": {
        "is_oa": true,
        "oa_status": "hybrid",
        "oa_url": "https://academic.oup.com/past/article-pdf/244/1/123/29021722/gtz010.pdf",
        "any_repository_has_fulltext": true
      },
      "locations": [
        {
          "is_oa": true,
          "landing_page_url": "https://doi.org/10.1093/pastj/gtz006",
          "pdf_url": "https://academic.oup.com/past/article-pdf/244/1/123/29021722/gtz010.pdf",
          "source": {
            "id": "https://openalex.org/S42922845",
            "display_name": "Past & Present",
            "issn_l": "0031-2746",
            "issn": [
              "0031-2746",
              "1477-464X"
            ],
            "is_oa": false,
            "is_in_doaj": false,
            "is_indexed_in_scopus": true,
            "is_core": false,
            "host_organization": "https://openalex.org/P4310311648",
            "host_organization_name": "Oxford University Press",
            "host_organization_lineage": [
              "https://openalex.org/P4310311647",
              "https://openalex.org/P4310311648"
            ],
            "host_organization_lineage_names": [
              "University of Oxford",
              "Oxford University Press"
            ],
            "type": "journal"
          },
          "license": "cc-by-nc-nd",
          "license_id": "https://openalex.org/licenses/cc-by-nc-nd",
          "version": "publishedVersion",
          "is_accepted": true,
          "is_published": true
        },
        {
          "is_oa": true,
          "landing_page_url": "https://www.openaccessrepository.it/record/45966",
          "pdf_url": "https://www.openaccessrepository.it/record/45966/files/fulltext.pdf",
          "source": {
            "id": "https://openalex.org/S4306402478",
            "display_name": "INFM-OAR (INFN Catania)",
            "issn_l": null,
            "issn": null,
            "is_oa": true,
            "is_in_doaj": false,
            "is_indexed_in_scopus": false,
            "is_core": false,
            "host_organization": "https://openalex.org/I4210116497",
            "host_organization_name": "Istituto Nazionale di Fisica Nucleare, Sezione di Catania",
            "host_organization_lineage": [
              "https://openalex.org/I4210116497"
            ],
            "host_organization_lineage_names": [
              "Istituto Nazionale di Fisica Nucleare, Sezione di Catania"
            ],
            "type": "repository"
          },
          "license": "other-oa",
          "license_id": "https://openalex.org/licenses/other-oa",
          "version": "publishedVersion",
          "is_accepted": true,
          "is_published": true
        }
      ],
      "best_oa_location": {
        "is_oa": true,
        "landing_page_url": "https://doi.org/10.1093/pastj/gtz006",
        "pdf_url": "https://academic.oup.com/past/article-pdf/244/1/123/29021722/gtz010.pdf",
        "source": {
          "id": "https://openalex.org/S42922845",
          "display_name": "Past & Present",
          "issn_l": "0031-2746",
          "issn": [
            "0031-2746",
            "1477-464X"
          ],
          "is_oa": false,
          "is_in_doaj": false,
          "is_indexed_in_scopus": true,
          "is_core": false,
          "host_organization": "https://openalex.org/P4310311648",
          "host_organization_name": "Oxford University Press",
          "host_organization_lineage": [
            "https://openalex.org/P4310311647",
            "https://openalex.org/P4310311648"
          ],
          "host_organization_lineage_names": [
            "University of Oxford",
            "Oxford University Press"
          ],
          "type": "journal"
        },
        "license": "cc-by-nc-nd",
        "license_id": "https://openalex.org/licenses/cc-by-nc-nd",
        "version": "publishedVersion",
        "is_accepted": true,
        "is_published": true
      }
    }
  },
  {
    "id": "https://openalex.org/W2133230377",
    "title": "Why design history? A multi-national perspective on the state and purpose of the field",
    "relevance_score": 1.4732021,
    "doi": "https://doi.org/10.1177/1474022212467601",
    "topic_ids": [
      "C2778061430",
      "C144024400",
      "C98184364",
      "C2775884927",
      "C106306483",
      "C2777855551",
      "C12713177",
      "C48103436",
      "C9652623",
      "C182306322",
      "C36289849",
      "C55587333",
      "C17744445",
      "C127413603",
      "C153349607",
      "C199539241",
      "C161191863",
      "C78519656",
      "C142362112",
      "C55493867",
      "C185592680",
      "C33923547",
      "C11413529",
      "C41008148",
      "C106159729",
      "C202444582",
      "C162324750",
      "C10138342"
    ],
    "best_pdf": "http://uhra.herts.ac.uk/bitstream/2299/10740/2/904910.pdf",
    "backup_pdf": "http://hdl.handle.net/2299/10740",
    "raw": {
      "id": "https://openalex.org/W2133230377",
      "display_name": "Why design history? A multi-national perspective on the state and purpose of the field",
      "relevance_score": 1.4732021,
      "doi": "https://doi.org/10.1177/1474022212467601",
      "concepts": [
        {
          "id": "https://openalex.org/C2778061430",
          "wikidata": "https://www.wikidata.org/wiki/Q188823",
          "display_name": "Scholarship",
          "level": 2,
          "score": 0.64893144
        },
        {
          "id": "https://openalex.org/C144024400",
          "wikidata": "https://www.wikidata.org/wiki/Q21201",
          "display_name": "Sociology",
          "level": 0,
          "score": 0.5524706
        },
        {
          "id": "https://openalex.org/C98184364",
          "wikidata": "https://www.wikidata.org/wiki/Q1780131",
          "display_name": "Argument (complex analysis)",
          "level": 2,
          "score": 0.537117
        },
        {
          "id": "https://openalex.org/C2775884927",
          "wikidata": "https://www.wikidata.org/wiki/Q1200703",
          "display_name": "Design history",
          "level": 2,
          "score": 0.49856043
        },
        {
          "id": "https://openalex.org/C106306483",
          "wikidata": "https://www.wikidata.org/wiki/Q183984",
          "display_name": "Futures contract",
          "level": 2,
          "score": 0.4905705
        },
        {
          "id": "https://openalex.org/C2777855551",
          "wikidata": "https://www.wikidata.org/wiki/Q12310021",
          "display_name": "Subject (documents)",
          "level": 2,
          "score": 0.47660655
        },
        {
          "id": "https://openalex.org/C12713177",
          "wikidata": "https://www.wikidata.org/wiki/Q1900281",
          "display_name": "Perspective (graphical)",
          "level": 2,
          "score": 0.47507566
        },
        {
          "id": "https://openalex.org/C48103436",
          "wikidata": "https://www.wikidata.org/wiki/Q599031",
          "display_name": "State (computer science)",
          "level": 2,
          "score": 0.45916587
        },
        {
          "id": "https://openalex.org/C9652623",
          "wikidata": "https://www.wikidata.org/wiki/Q190109",
          "display_name": "Field (mathematics)",
          "level": 2,
          "score": 0.44515523
        },
        {
          "id": "https://openalex.org/C182306322",
          "wikidata": "https://www.wikidata.org/wiki/Q1779371",
          "display_name": "Order (exchange)",
          "level": 2,
          "score": 0.41898105
        },
        {
          "id": "https://openalex.org/C36289849",
          "wikidata": "https://www.wikidata.org/wiki/Q34749",
          "display_name": "Social science",
          "level": 1,
          "score": 0.38488346
        },
        {
          "id": "https://openalex.org/C55587333",
          "wikidata": "https://www.wikidata.org/wiki/Q1133029",
          "display_name": "Engineering ethics",
          "level": 1,
          "score": 0.36620986
        },
        {
          "id": "https://openalex.org/C17744445",
          "wikidata": "https://www.wikidata.org/wiki/Q36442",
          "display_name": "Political science",
          "level": 0,
          "score": 0.21392995
        },
        {
          "id": "https://openalex.org/C127413603",
          "wikidata": "https://www.wikidata.org/wiki/Q11023",
          "display_name": "Engineering",
          "level": 0,
          "score": 0.15139124
        },
        {
          "id": "https://openalex.org/C153349607",
          "wikidata": "https://www.wikidata.org/wiki/Q36649",
          "display_name": "Visual arts",
          "level": 1,
          "score": 0.13270685
        },
        {
          "id": "https://openalex.org/C199539241",
          "wikidata": "https://www.wikidata.org/wiki/Q7748",
          "display_name": "Law",
          "level": 1,
          "score": 0.12483838
        },
        {
          "id": "https://openalex.org/C161191863",
          "wikidata": "https://www.wikidata.org/wiki/Q199655",
          "display_name": "Library science",
          "level": 1,
          "score": 0.10869673
        },
        {
          "id": "https://openalex.org/C78519656",
          "wikidata": "https://www.wikidata.org/wiki/Q101333",
          "display_name": "Mechanical engineering",
          "level": 1,
          "score": 0.0
        },
        {
          "id": "https://openalex.org/C142362112",
          "wikidata": "https://www.wikidata.org/wiki/Q735",
          "display_name": "Art",
          "level": 0,
          "score": 0.0
        },
        {
          "id": "https://openalex.org/C55493867",
          "wikidata": "https://www.wikidata.org/wiki/Q7094",
          "display_name": "Biochemistry",
          "level": 1,
          "score": 0.0
        },
        {
          "id": "https://openalex.org/C185592680",
          "wikidata": "https://www.wikidata.org/wiki/Q2329",
          "display_name": "Chemistry",
          "level": 0,
          "score": 0.0
        },
        {
          "id": "https://openalex.org/C33923547",
          "wikidata": "https://www.wikidata.org/wiki/Q395",
          "display_name": "Mathematics",
          "level": 0,
          "score": 0.0
        },
        {
          "id": "https://openalex.org/C11413529",
          "wikidata": "https://www.wikidata.org/wiki/Q8366",
          "display_name": "Algorithm",
          "level": 1,
          "score": 0.0
        },
        {
          "id": "https://openalex.org/C41008148",
          "wikidata": "https://www.wikidata.org/wiki/Q21198",
          "display_name": "Computer science",
          "level": 0,
          "score": 0.0
        },
        {
          "id": "https://openalex.org/C106159729",
          "wikidata": "https://www.wikidata.org/wiki/Q2294553",
          "display_name": "Financial economics",
          "level": 1,
          "score": 0.0
        },
        {
          "id": "https://openalex.org/C202444582",
          "wikidata": "https://www.wikidata.org/wiki/Q837863",
          "display_name": "Pure mathematics",
          "level": 1,
          "score": 0.0
        },
        {
          "id": "https://openalex.org/C162324750",
          "wikidata": "https://www.wikidata.org/wiki/Q8134",
          "display_name": "Economics",
          "level": 0,
          "score": 0.0
        },
        {
          "id": "https://openalex.org/C10138342",
          "wikidata": "https://www.wikidata.org/wiki/Q43015",
          "display_name": "Finance",
          "level": 1,
          "score": 0.0
        }
      ],
      "primary_location": {
        "is_oa": false,
        "landing_page_url": "https://doi.org/10.1177/1474022212467601",
        "pdf_url": null,
        "source": {
          "id": "https://openalex.org/S97967959",
          "display_name": "Arts and Humanities in Higher Education",
          "issn_l": "1474-0222",
          "issn": [
            "1474-0222",
            "1741-265X"
          ],
          "is_oa": false,
          "is_in_doaj": false,
          "is_indexed_in_scopus": true,
          "is_core": true,
          "host_organization": "https://openalex.org/P4310320017",
          "host_organization_name": "SAGE Publishing",
          "host_organization_lineage": [
            "https://openalex.org/P4310320017"
          ],
          "host_organization_lineage_names": [
            "SAGE Publishing"
          ],
          "type": "journal"
        },
        "license": null,
        "license_id": null,
        "version": null,
        "is_accepted": false,
        "is_published": false
      },
      "open_access": {
        "is_oa": true,
        "oa_status": "green",
        "oa_url": "http://uhra.herts.ac.uk/bitstream/2299/10740/2/904910.pdf",
        "any_repository_has_fulltext": true
      },
      "locations": [
        {
          "is_oa": false,
          "landing_page_url": "https://doi.org/10.1177/1474022212467601",
          "pdf_url": null,
          "source": {
            "id": "https://openalex.org/S97967959",
            "display_name": "Arts and Humanities in Higher Education",
            "issn_l": "1474-0222",
            "issn": [
              "1474-0222",
              "1741-265X"
            ],
            "is_oa": false,
            "is_in_doaj": false,
            "is_indexed_in_scopus": true,
            "is_core": true,
            "host_organization": "https://openalex.org/P4310320017",
            "host_organization_name": "SAGE Publishing",
            "host_organization_lineage": [
              "https://openalex.org/P4310320017"
            ],
            "host_organization_lineage_names": [
              "SAGE Publishing"
            ],
            "type": "journal"
          },
          "license": null,
          "license_id": null,
          "version": null,
          "is_accepted": false,
          "is_published": false
        },
        {
          "is_oa": true,
          "landing_page_url": "http://hdl.handle.net/2299/10740",
          "pdf_url": "http://uhra.herts.ac.uk/bitstream/2299/10740/2/904910.pdf",
          "source": {
            "id": "https://openalex.org/S4306400241",
            "display_name": "University of Hertfordshire Research Archive (University of Hertfordshire)",
            "issn_l": null,
            "issn": null,
            "is_oa": true,
            "is_in_doaj": false,
            "is_indexed_in_scopus": false,
            "is_core": false,
            "host_organization": "https://openalex.org/I141584323",
            "host_organization_name": "University of Hertfordshire",
            "host_organization_lineage": [
              "https://openalex.org/I141584323"
            ],
            "host_organization_lineage_names": [
              "University of Hertfordshire"
            ],
            "type": "repository"
          },
          "license": null,
          "license_id": null,
          "version": "submittedVersion",
          "is_accepted": false,
          "is_published": false
        }
      ],
      "best_oa_location": {
        "is_oa": true,
        "landing_page_url": "http://hdl.handle.net/2299/10740",
        "pdf_url": "http://uhra.herts.ac.uk/bitstream/2299/10740/2/904910.pdf",
        "source": {
          "id": "https://openalex.org/S4306400241",
          "display_name": "University of Hertfordshire Research Archive (University of Hertfordshire)",
          "issn_l": null,
          "issn": null,
          "is_oa": true,
          "is_in_doaj": false,
          "is_indexed_in_scopus": false,
          "is_core": false,
          "host_organization": "https://openalex.org/I141584323",
          "host_organization_name": "University of Hertfordshire",
          "host_organization_lineage": [
            "https://openalex.org/I141584323"
          ],
          "host_organization_lineage_names": [
            "University of Hertfordshire"
          ],
          "type": "repository"
        },
        "license": null,
        "license_id": null,
        "version": "submittedVersion",
        "is_accepted": false,
        "is_published": false
      }
    }
  }
]