[
  {
    "id": "https://openalex.org/W4242988031",
    "title": "Did Joshua Reynolds Paint His Pictures? The Transatlantic Work of Picturing in an Age of Chymical Reproduction",
    "relevance_score": 1.0789764,
    "doi": "https://doi.org/10.37862/aaeportal.00190.002",
    "topic_ids": [
      "C67101536",
      "C142362112",
      "C52119013",
      "C2780966255",
      "C554144382",
      "C70789860",
      "C2777855551",
      "C153349607",
      "C95457728",
      "C74916050",
      "C161191863",
      "C166957645",
      "C41008148"
    ],
    "best_pdf": "http://escholarship.mcgill.ca/downloads/7m01bq43g",
    "backup_pdf": "https://escholarship.mcgill.ca/concern/articles/1g05fg75w",
    "raw": {
      "id": "https://openalex.org/W4242988031",
      "display_name": "Did Joshua Reynolds Paint His Pictures? The Transatlantic Work of Picturing in an Age of Chymical Reproduction",
      "relevance_score": 1.0789764,
      "doi": "https://doi.org/10.37862/aaeportal.00190.002",
      "concepts": [
        {
          "id": "https://openalex.org/C67101536",
          "wikidata": "https://www.wikidata.org/wiki/Q5535910",
          "display_name": "George (robot)",
          "level": 2,
          "score": 0.8051482
        },
        {
          "id": "https://openalex.org/C142362112",
          "wikidata": "https://www.wikidata.org/wiki/Q735",
          "display_name": "Art",
          "level": 0,
          "score": 0.63614386
        },
        {
          "id": "https://openalex.org/C52119013",
          "wikidata": "https://www.wikidata.org/wiki/Q50637",
          "display_name": "Art history",
          "level": 1,
          "score": 0.59009355
        },
        {
          "id": "https://openalex.org/C2780966255",
          "wikidata": "https://www.wikidata.org/wiki/Q5474306",
          "display_name": "Foundation (evidence)",
          "level": 2,
          "score": 0.582424
        },
        {
          "id": "https://openalex.org/C554144382",
          "wikidata": "https://www.wikidata.org/wiki/Q213156",
          "display_name": "Performance art",
          "level": 2,
          "score": 0.53084385
        },
        {
          "id": "https://openalex.org/C70789860",
          "wikidata": "https://www.wikidata.org/wiki/Q2018526",
          "display_name": "The arts",
          "level": 2,
          "score": 0.50250626
        },
        {
          "id": "https://openalex.org/C2777855551",
          "wikidata": "https://www.wikidata.org/wiki/Q12310021",
          "display_name": "Subject (documents)",
          "level": 2,
          "score": 0.47912762
        },
        {
          "id": "https://openalex.org/C153349607",
          "wikidata": "https://www.wikidata.org/wiki/Q36649",
          "display_name": "Visual arts",
          "level": 1,
          "score": 0.40758878
        },
        {
          "id": "https://openalex.org/C95457728",
          "wikidata": "https://www.wikidata.org/wiki/Q309",
          "display_name": "History",
          "level": 0,
          "score": 0.38302743
        },
        {
          "id": "https://openalex.org/C74916050",
          "wikidata": "https://www.wikidata.org/wiki/Q841090",
          "display_name": "Classics",
          "level": 1,
          "score": 0.34852713
        },
        {
          "id": "https://openalex.org/C161191863",
          "wikidata": "https://www.wikidata.org/wiki/Q199655",
          "display_name": "Library science",
          "level": 1,
          "score": 0.13726741
        },
        {
          "id": "https://openalex.org/C166957645",
          "wikidata": "https://www.wikidata.org/wiki/Q23498",
          "display_name": "Archaeology",
          "level": 1,
          "score": 0.11863753
        },
        {
          "id": "https://openalex.org/C41008148",
          "wikidata": "https://www.wikidata.org/wiki/Q21198",
          "display_name": "Computer science",
          "level": 0,
          "score": 0.050988644
        }
      ],
      "primary_location": {
        "is_oa": false,
        "landing_page_url": "https://doi.org/10.37862/aaeportal.00190.002",
        "pdf_url": null,
        "source": null,
        "license": null,
        "license_id": null,
        "version": null,
        "is_accepted": false,
        "is_published": false
      },
      "open_access": {
        "is_oa": true,
        "oa_status": "green",
        "oa_url": "http://escholarship.mcgill.ca/downloads/7m01bq43g",
        "any_repository_has_fulltext": true
      },
      "locations": [
        {
          "is_oa": false,
          "landing_page_url": "https://doi.org/10.37862/aaeportal.00190.002",
          "pdf_url": null,
          "source": null,
          "license": null,
          "license_id": null,
          "version": null,
          "is_accepted": false,
          "is_published": false
        },
        {
          "is_oa": true,
          "landing_page_url": "https://escholarship.mcgill.ca/concern/articles/1g05fg75w",
          "pdf_url": "http://escholarship.mcgill.ca/downloads/7m01bq43g",
          "source": {
            "id": "https://openalex.org/S4306401568",
            "display_name": "eScholarship@McGill (McGill)",
            "issn_l": null,
            "issn": null,
            "is_oa": true,
            "is_in_doaj": false,
            "is_indexed_in_scopus": false,
            "is_core": false,
            "host_organization": "https://openalex.org/I5023651",
            "host_organization_name": "McGill University",
            "host_organization_lineage": [
              "https://openalex.org/I5023651"
            ],
            "host_organization_lineage_names": [
              "McGill University"
            ],
            "type": "repository"
          },
          "license": null,
          "license_id": null,
          "version": "submittedVersion",
          "is_accepted": false,
          "is_published": false
        }
      ],
      "best_oa_location": {
        "is_oa": true,
        "landing_page_url": "https://escholarship.mcgill.ca/concern/articles/1g05fg75w",
        "pdf_url": "http://escholarship.mcgill.ca/downloads/7m01bq43g",
        "source": {
          "id": "https://openalex.org/S4306401568",
          "display_name": "eScholarship@McGill (McGill)",
          "issn_l": null,
          "issn": null,
          "is_oa": true,
          "is_in_doaj": false,
          "is_indexed_in_scopus": false,
          "is_core": false,
          "host_organization": "https://openalex.org/I5023651",
          "host_organization_name": "McGill University",
          "host_organization_lineage": [
            "https://openalex.org/I5023651"
          ],
          "host_organization_lineage_names": [
            "McGill University"
          ],
          "type": "repository"
        },
        "license": null,
        "license_id": null,
        "version": "submittedVersion",
        "is_accepted": false,
        "is_published": false
      }
    }
  },
  {
    "id": "https://openalex.org/W2773090700",
    "title": "'The Snob’s Chaldron': Alexander Davison and the Private Patronage of History Painting in Early Nineteenth-Century Britain",
    "relevance_score": 1.0404153,
    "doi": "https://doi.org/10.17658/issn.2058-5462/issue-07/kgazzard",
    "topic_ids": [
      "C205783811",
      "C142362112",
      "C52119013",
      "C153349607",
      "C123657996",
      "C95457728"
    ],
    "best_pdf": "http://pdf.britishartstudies.ac.uk/articles/issue-7-alexander-davison.pdf",
    "backup_pdf": "https://doi.org/10.17658/issn.2058-5462/issue-07/kgazzard",
    "raw": {
      "id": "https://openalex.org/W2773090700",
      "display_name": "'The Snob’s Chaldron': Alexander Davison and the Private Patronage of History Painting in Early Nineteenth-Century Britain",
      "relevance_score": 1.0404153,
      "doi": "https://doi.org/10.17658/issn.2058-5462/issue-07/kgazzard",
      "concepts": [
        {
          "id": "https://openalex.org/C205783811",
          "wikidata": "https://www.wikidata.org/wiki/Q11629",
          "display_name": "Painting",
          "level": 2,
          "score": 0.87968946
        },
        {
          "id": "https://openalex.org/C142362112",
          "wikidata": "https://www.wikidata.org/wiki/Q735",
          "display_name": "Art",
          "level": 0,
          "score": 0.53860193
        },
        {
          "id": "https://openalex.org/C52119013",
          "wikidata": "https://www.wikidata.org/wiki/Q50637",
          "display_name": "Art history",
          "level": 1,
          "score": 0.5131098
        },
        {
          "id": "https://openalex.org/C153349607",
          "wikidata": "https://www.wikidata.org/wiki/Q36649",
          "display_name": "Visual arts",
          "level": 1,
          "score": 0.47914928
        },
        {
          "id": "https://openalex.org/C123657996",
          "wikidata": "https://www.wikidata.org/wiki/Q12271",
          "display_name": "Architecture",
          "level": 2,
          "score": 0.44896343
        },
        {
          "id": "https://openalex.org/C95457728",
          "wikidata": "https://www.wikidata.org/wiki/Q309",
          "display_name": "History",
          "level": 0,
          "score": 0.40295708
        }
      ],
      "primary_location": {
        "is_oa": true,
        "landing_page_url": "https://doi.org/10.17658/issn.2058-5462/issue-07/kgazzard",
        "pdf_url": "http://pdf.britishartstudies.ac.uk/articles/issue-7-alexander-davison.pdf",
        "source": {
          "id": "https://openalex.org/S2738754793",
          "display_name": "British Art Studies",
          "issn_l": "2058-5462",
          "issn": [
            "2058-5462"
          ],
          "is_oa": true,
          "is_in_doaj": true,
          "is_indexed_in_scopus": false,
          "is_core": false,
          "host_organization": "https://openalex.org/P4310315589",
          "host_organization_name": "Yale University",
          "host_organization_lineage": [
            "https://openalex.org/P4310315589"
          ],
          "host_organization_lineage_names": [
            "Yale University"
          ],
          "type": "journal"
        },
        "license": "cc-by-nc",
        "license_id": "https://openalex.org/licenses/cc-by-nc",
        "version": "publishedVersion",
        "is_accepted": true,
        "is_published": true
      },
      "open_access": {
        "is_oa": true,
        "oa_status": "diamond",
        "oa_url": "http://pdf.britishartstudies.ac.uk/articles/issue-7-alexander-davison.pdf",
        "any_repository_has_fulltext": false
      },
      "locations": [
        {
          "is_oa": true,
          "landing_page_url": "https://doi.org/10.17658/issn.2058-5462/issue-07/kgazzard",
          "pdf_url": "http://pdf.britishartstudies.ac.uk/articles/issue-7-alexander-davison.pdf",
          "source": {
            "id": "https://openalex.org/S2738754793",
            "display_name": "British Art Studies",
            "issn_l": "2058-5462",
            "issn": [
              "2058-5462"
            ],
            "is_oa": true,
            "is_in_doaj": true,
            "is_indexed_in_scopus": false,
            "is_core": false,
            "host_organization": "https://openalex.org/P4310315589",
            "host_organization_name": "Yale University",
            "host_organization_lineage": [
              "https://openalex.org/P4310315589"
            ],
            "host_organization_lineage_names": [
              "Yale University"
            ],
            "type": "journal"
          },
          "license": "cc-by-nc",
          "license_id": "https://openalex.org/licenses/cc-by-nc",
          "version": "publishedVersion",
          "is_accepted": true,
          "is_published": true
        },
        {
          "is_oa": false,
          "landing_page_url": "https://doaj.org/article/7aca3de8560b4018a31bb343700ef81b",
          "pdf_url": null,
          "source": {
            "id": "https://openalex.org/S4306401280",
            "display_name": "DOAJ (DOAJ: Directory of Open Access Journals)",
            "issn_l": null,
            "issn": null,
            "is_oa": true,
            "is_in_doaj": false,
            "is_indexed_in_scopus": false,
            "is_core": false,
            "host_organization": null,
            "host_organization_name": null,
            "host_organization_lineage": [],
            "host_organization_lineage_names": [],
            "type": "repository"
          },
          "license": null,
          "license_id": null,
          "version": null,
          "is_accepted": false,
          "is_published": false
        }
      ],
      "best_oa_location": {
        "is_oa": true,
        "landing_page_url": "https://doi.org/10.17658/issn.2058-5462/issue-07/kgazzard",
        "pdf_url": "http://pdf.britishartstudies.ac.uk/articles/issue-7-alexander-davison.pdf",
        "source": {
          "id": "https://openalex.org/S2738754793",
          "display_name": "British Art Studies",
          "issn_l": "2058-5462",
          "issn": [
            "2058-5462"
          ],
          "is_oa": true,
          "is_in_doaj": true,
          "is_indexed_in_scopus": false,
          "is_core": false,
          "host_organization": "https://openalex.org/P4310315589",
          "host_organization_name": "Yale University",
          "host_organization_lineage": [
            "https://openalex.org/P4310315589"
          ],
          "host_organization_lineage_names": [
            "Yale University"
          ],
          "type": "journal"
        },
        "license": "cc-by-nc",
        "license_id": "https://openalex.org/licenses/cc-by-nc",
        "version": "publishedVersion",
        "is_accepted": true,
        "is_published": true
      }
    }
  },
  {
    "id": "https://openalex.org/W4205998586",
    "title": "In the steps of the Prophets: The dissemination and reinterpretation of David Roberts’ Holy Lands sketches through the Shows of London",
    "relevance_score": 1.0067856,
    "doi": "https://doi.org/10.32926/2021.10.bro.jerem",
    "topic_ids": [
      "C37531588",
      "C2778734905",
      "C2779448473",
      "C178288346",
      "C205783811",
      "C2778692574",
      "C2781291010",
      "C95457728",
      "C142362112",
      "C144024400",
      "C52119013",
      "C107038049",
      "C138885662",
      "C27206212",
      "C166957645"
    ],
    "best_pdf": "https://www.mutualimages-journal.org/index.php/mi/article/download/105/10-7",
    "backup_pdf": "https://doi.org/10.32926/2021.10.bro.jerem",
    "raw": {
      "id": "https://openalex.org/W4205998586",
      "display_name": "In the steps of the Prophets: The dissemination and reinterpretation of David Roberts’ Holy Lands sketches through the Shows of London",
      "relevance_score": 1.0067856,
      "doi": "https://doi.org/10.32926/2021.10.bro.jerem",
      "concepts": [
        {
          "id": "https://openalex.org/C37531588",
          "wikidata": "https://www.wikidata.org/wiki/Q464980",
          "display_name": "Exhibition",
          "level": 2,
          "score": 0.8484563
        },
        {
          "id": "https://openalex.org/C2778734905",
          "wikidata": "https://www.wikidata.org/wiki/Q15130689",
          "display_name": "Reinterpretation",
          "level": 2,
          "score": 0.8382759
        },
        {
          "id": "https://openalex.org/C2779448473",
          "wikidata": "https://www.wikidata.org/wiki/Q1644573",
          "display_name": "Pilgrimage",
          "level": 2,
          "score": 0.8050614
        },
        {
          "id": "https://openalex.org/C178288346",
          "wikidata": "https://www.wikidata.org/wiki/Q1123855",
          "display_name": "Contemplation",
          "level": 2,
          "score": 0.67805785
        },
        {
          "id": "https://openalex.org/C205783811",
          "wikidata": "https://www.wikidata.org/wiki/Q11629",
          "display_name": "Painting",
          "level": 2,
          "score": 0.58204865
        },
        {
          "id": "https://openalex.org/C2778692574",
          "wikidata": "https://www.wikidata.org/wiki/Q5410500",
          "display_name": "Faith",
          "level": 2,
          "score": 0.5806519
        },
        {
          "id": "https://openalex.org/C2781291010",
          "wikidata": "https://www.wikidata.org/wiki/Q178580",
          "display_name": "Period (music)",
          "level": 2,
          "score": 0.5347181
        },
        {
          "id": "https://openalex.org/C95457728",
          "wikidata": "https://www.wikidata.org/wiki/Q309",
          "display_name": "History",
          "level": 0,
          "score": 0.45740986
        },
        {
          "id": "https://openalex.org/C142362112",
          "wikidata": "https://www.wikidata.org/wiki/Q735",
          "display_name": "Art",
          "level": 0,
          "score": 0.3686487
        },
        {
          "id": "https://openalex.org/C144024400",
          "wikidata": "https://www.wikidata.org/wiki/Q21201",
          "display_name": "Sociology",
          "level": 0,
          "score": 0.357926
        },
        {
          "id": "https://openalex.org/C52119013",
          "wikidata": "https://www.wikidata.org/wiki/Q50637",
          "display_name": "Art history",
          "level": 1,
          "score": 0.34442323
        },
        {
          "id": "https://openalex.org/C107038049",
          "wikidata": "https://www.wikidata.org/wiki/Q35986",
          "display_name": "Aesthetics",
          "level": 1,
          "score": 0.3440865
        },
        {
          "id": "https://openalex.org/C138885662",
          "wikidata": "https://www.wikidata.org/wiki/Q5891",
          "display_name": "Philosophy",
          "level": 0,
          "score": 0.23121884
        },
        {
          "id": "https://openalex.org/C27206212",
          "wikidata": "https://www.wikidata.org/wiki/Q34178",
          "display_name": "Theology",
          "level": 1,
          "score": 0.17007169
        },
        {
          "id": "https://openalex.org/C166957645",
          "wikidata": "https://www.wikidata.org/wiki/Q23498",
          "display_name": "Archaeology",
          "level": 1,
          "score": 0.1486617
        }
      ],
      "primary_location": {
        "is_oa": true,
        "landing_page_url": "https://doi.org/10.32926/2021.10.bro.jerem",
        "pdf_url": "https://www.mutualimages-journal.org/index.php/mi/article/download/105/10-7",
        "source": {
          "id": "https://openalex.org/S4210177230",
          "display_name": "Mutual Images Journal",
          "issn_l": "2496-1868",
          "issn": [
            "2496-1868"
          ],
          "is_oa": true,
          "is_in_doaj": false,
          "is_indexed_in_scopus": false,
          "is_core": false,
          "host_organization": null,
          "host_organization_name": null,
          "host_organization_lineage": [],
          "host_organization_lineage_names": [],
          "type": "journal"
        },
        "license": null,
        "license_id": null,
        "version": "publishedVersion",
        "is_accepted": true,
        "is_published": true
      },
      "open_access": {
        "is_oa": true,
        "oa_status": "gold",
        "oa_url": "https://www.mutualimages-journal.org/index.php/mi/article/download/105/10-7",
        "any_repository_has_fulltext": true
      },
      "locations": [
        {
          "is_oa": true,
          "landing_page_url": "https://doi.org/10.32926/2021.10.bro.jerem",
          "pdf_url": "https://www.mutualimages-journal.org/index.php/mi/article/download/105/10-7",
          "source": {
            "id": "https://openalex.org/S4210177230",
            "display_name": "Mutual Images Journal",
            "issn_l": "2496-1868",
            "issn": [
              "2496-1868"
            ],
            "is_oa": true,
            "is_in_doaj": false,
            "is_indexed_in_scopus": false,
            "is_core": false,
            "host_organization": null,
            "host_organization_name": null,
            "host_organization_lineage": [],
            "host_organization_lineage_names": [],
            "type": "journal"
          },
          "license": null,
          "license_id": null,
          "version": "publishedVersion",
          "is_accepted": true,
          "is_published": true
        },
        {
          "is_oa": true,
          "landing_page_url": "http://mutualimages-journal.org/index.php/mi/article/view/105",
          "pdf_url": "https://mutualimages-journal.org/index.php/mi/article/download/105/10-7",
          "source": {
            "id": "https://openalex.org/S4306401474",
            "display_name": "Mutual Images Journal (Mutual Images Research Association)",
            "issn_l": null,
            "issn": null,
            "is_oa": true,
            "is_in_doaj": false,
            "is_indexed_in_scopus": false,
            "is_core": false,
            "host_organization": null,
            "host_organization_name": null,
            "host_organization_lineage": [],
            "host_organization_lineage_names": [],
            "type": "repository"
          },
          "license": "cc-by",
          "license_id": "https://openalex.org/licenses/cc-by",
          "version": "publishedVersion",
          "is_accepted": true,
          "is_published": true
        }
      ],
      "best_oa_location": {
        "is_oa": true,
        "landing_page_url": "https://doi.org/10.32926/2021.10.bro.jerem",
        "pdf_url": "https://www.mutualimages-journal.org/index.php/mi/article/download/105/10-7",
        "source": {
          "id": "https://openalex.org/S4210177230",
          "display_name": "Mutual Images Journal",
          "issn_l": "2496-1868",
          "issn": [
            "2496-1868"
          ],
          "is_oa": true,
          "is_in_doaj": false,
          "is_indexed_in_scopus": false,
          "is_core": false,
          "host_organization": null,
          "host_organization_name": null,
          "host_organization_lineage": [],
          "host_organization_lineage_names": [],
          "type": "journal"
        },
        "license": null,
        "license_id": null,
        "version": "publishedVersion",
        "is_accepted": true,
        "is_published": true
      }
    }
  }
]